guacenc/__init__.py
guacenc/__main__.py
guacenc/cli.py
guacenc/guacenc_encode.py
guacenc/guacenc_instruction.py
guacenc/guacenc_parse.py
guacenc/guacenc_types.py
guacenc_py-0.1.3.dist-info/licenses/LICENSE
guacenc_py-0.1.3.dist-info/METADATA
guacenc_py-0.1.3.dist-info/WHEEL
guacenc_py-0.1.3.dist-info/entry_points.txt
guacenc_py-0.1.3.dist-info/top_level.txt
guacenc_py-0.1.3.dist-info/RECORD
