Metadata-Version: 2.4
Name: guacenc-py
Version: 0.1.3
Summary: Prue python version of guacenc
Author-email: Eric <xplzv@126.com>
License-Expression: Apache-2.0
Classifier: Programming Language :: Python :: 3
Requires-Python: >=3.9
License-File: LICENSE
Requires-Dist: pillow>=11.1.0
Requires-Dist: pycairo>=1.27.0
Requires-Dist: tqdm>=4.67.1
Dynamic: license-file
